vinzy_imgdata_importer/__init__.py
vinzy_imgdata_importer-1.0.2.dist-info/LICENSE
vinzy_imgdata_importer-1.0.2.dist-info/METADATA
vinzy_imgdata_importer-1.0.2.dist-info/WHEEL
vinzy_imgdata_importer-1.0.2.dist-info/top_level.txt
vinzy_imgdata_importer-1.0.2.dist-info/RECORD
