Metadata-Version: 2.1
Name: vinzy-imgdata-importer
Version: 1.0.2
Summary: This Package will help you to import image data for your deep learning project
Home-page: https://github.com/vinayak-97/Image-data-importer-for-deep-learning
Author: Vinayak Bhosale
Author-email: vinubhosale.cj@gmail.com
License: MIT
Platform: UNKNOWN
Classifier: License :: OSI Approved :: MIT License
Classifier: Programming Language :: Python :: 3
Classifier: Programming Language :: Python :: 3.7
Requires-Dist: numpy
Requires-Dist: opencv-python
Requires-Dist: pickle-mixin
